ytmusicapi/__init__.py
ytmusicapi/constants.py
ytmusicapi/continuations.py
ytmusicapi/helpers.py
ytmusicapi/navigation.py
ytmusicapi/setup.py
ytmusicapi/ytmusic.py
ytmusicapi/auth/__init__.py
ytmusicapi/auth/browser.py
ytmusicapi/auth/headers.py
ytmusicapi/auth/oauth.py
ytmusicapi/locales/README.rst
ytmusicapi/locales/ar/LC_MESSAGES/base.mo
ytmusicapi/locales/de/LC_MESSAGES/base.mo
ytmusicapi/locales/en/LC_MESSAGES/base.mo
ytmusicapi/locales/es/LC_MESSAGES/base.mo
ytmusicapi/locales/fr/LC_MESSAGES/base.mo
ytmusicapi/locales/hi/LC_MESSAGES/base.mo
ytmusicapi/locales/it/LC_MESSAGES/base.mo
ytmusicapi/locales/ja/LC_MESSAGES/base.mo
ytmusicapi/locales/ko/LC_MESSAGES/base.mo
ytmusicapi/locales/nl/LC_MESSAGES/base.mo
ytmusicapi/locales/pt/LC_MESSAGES/base.mo
ytmusicapi/locales/ru/LC_MESSAGES/base.mo
ytmusicapi/locales/tr/LC_MESSAGES/base.mo
ytmusicapi/locales/ur/LC_MESSAGES/base.mo
ytmusicapi/locales/zh_CN/LC_MESSAGES/base.mo
ytmusicapi/locales/zh_TW/LC_MESSAGES/base.mo
ytmusicapi/mixins/__init__.py
ytmusicapi/mixins/_utils.py
ytmusicapi/mixins/browsing.py
ytmusicapi/mixins/explore.py
ytmusicapi/mixins/library.py
ytmusicapi/mixins/playlists.py
ytmusicapi/mixins/search.py
ytmusicapi/mixins/uploads.py
ytmusicapi/mixins/watch.py
ytmusicapi/parsers/__init__.py
ytmusicapi/parsers/_utils.py
ytmusicapi/parsers/albums.py
ytmusicapi/parsers/browsing.py
ytmusicapi/parsers/explore.py
ytmusicapi/parsers/i18n.py
ytmusicapi/parsers/library.py
ytmusicapi/parsers/playlists.py
ytmusicapi/parsers/search.py
ytmusicapi/parsers/songs.py
ytmusicapi/parsers/uploads.py
ytmusicapi/parsers/watch.py
youtubemusicapifork-0.0.4.dist-info/LICENSE
youtubemusicapifork-0.0.4.dist-info/METADATA
youtubemusicapifork-0.0.4.dist-info/WHEEL
youtubemusicapifork-0.0.4.dist-info/entry_points.txt
youtubemusicapifork-0.0.4.dist-info/top_level.txt
youtubemusicapifork-0.0.4.dist-info/RECORD
