Metadata-Version: 2.1
Name: youtubemusicapifork
Version: 0.0.4
Summary: Fork of the unofficial API for YouTube Music
Author-email: davadams97 <david.adams97@gmail.com>
License: MIT License
Project-URL: homepage, https://github.com/davadams97/youtubemusicapi
Project-URL: documentation, https://ytmusicapi.readthedocs.io
Project-URL: repository, https://github.com/davadams97/youtubemusicapi
Classifier: Programming Language :: Python :: 3
Classifier: License :: OSI Approved :: MIT License
Requires-Python: >=3.8
License-File: LICENSE
Requires-Dist: requests >=2.22
Provides-Extra: dev
Requires-Dist: pre-commit ; extra == 'dev'
Requires-Dist: flake8 ; extra == 'dev'
Requires-Dist: yapf ; extra == 'dev'
Requires-Dist: coverage ; extra == 'dev'
Requires-Dist: sphinx ; extra == 'dev'
Requires-Dist: sphinx-rtd-theme ; extra == 'dev'
